geoip_api/__init__.py
geoip_api/config.py
geoip_api/exceptions.py
geoip_api/core/__init__.py
geoip_api/core/database.py
geoip_api/core/lookup.py
geoip_api/utils/__init__.py
geoip_api/utils/currency.py
geoip_api/utils/logging.py
geoip_py-1.0.2.dist-info/licenses/LICENSE
geoip_py-1.0.2.dist-info/METADATA
geoip_py-1.0.2.dist-info/WHEEL
geoip_py-1.0.2.dist-info/top_level.txt
geoip_py-1.0.2.dist-info/RECORD
