Metadata-Version: 2.4
Name: geoip-py
Version: 1.0.2
Summary: Self-hosted IP geolocation library and API with currency support that works completely offline!
Home-page: https://github.com/Malith-Rukshan/geoip-api
Author: Malith Rukshan
Author-email: hello@malith.dev
Classifier: Programming Language :: Python :: 3
Classifier: License :: OSI Approved :: MIT License
Classifier: Operating System :: OS Independent
Requires-Python: >=3.9
License-File: LICENSE
Requires-Dist: geoip2==5.1.0
Requires-Dist: requests>=2.32.3
Requires-Dist: pycountry>=24.6.1
Provides-Extra: dev
Requires-Dist: pytest>=6.0; extra == "dev"
Requires-Dist: black; extra == "dev"
Requires-Dist: isort; extra == "dev"
Requires-Dist: mypy; extra == "dev"
Requires-Dist: flake8; extra == "dev"
Dynamic: author
Dynamic: author-email
Dynamic: classifier
Dynamic: description
Dynamic: description-content-type
Dynamic: home-page
Dynamic: license-file
Dynamic: provides-extra
Dynamic: requires-dist
Dynamic: requires-python
Dynamic: summary
